{"id": "495d9f2c316b05ef092099ef9401a180", "sport_key": "americanfootball_nfl", "sport_title": "NFL", "commence_time": "2024-09-15T17:00:00Z", "home_team": "Washington Commanders", "away_team": "New York Giants", "bookmakers": [{"key": "draftkings", "title": "DraftKings", "markets": [{"key": "h2h", "last_update": "2024-08-23T14:29:51Z", "outcomes": [{"name": "New York Giants", "price": 2.2}, {"name": "Washington Commanders", "price": 1.7}]}]}, {"key": "williamhill_us", "title": "Caesars", "markets": [{"key": "h2h", "last_update": "2024-08-23T14:19:19Z", "outcomes": [{"name": "New York Giants", "price": 2.22}, {"name": "Washington Commanders", "price": 1.69}]}]}, {"key": "betrivers", "title": "BetRivers", "markets": [{"key": "h2h", "last_update": "2024-08-23T14:29:51Z", "outcomes": [{"name": "New York Giants", "price": 2.23}, {"name": "Washington Commanders", "price": 1.67}]}]}, {"key": "bovada", "title": "Bovada", "markets": [{"key": "h2h", "last_update": "2024-08-23T14:29:51Z", "outcomes": [{"name": "New York Giants", "price": 2.15}, {"name": "Washington Commanders", "price": 1.74}]}]}]}