{"id": "514ad4e46861e2aa51571079d75856b5", "sport_key": "americanfootball_nfl", "sport_title": "NFL", "commence_time": "2024-10-20T17:00:00Z", "home_team": "Atlanta Falcons", "away_team": "Seattle Seahawks", "bookmakers": [{"key": "draftkings", "title": "DraftKings", "markets": [{"key": "h2h", "last_update": "2024-08-23T14:29:51Z", "outcomes": [{"name": "Atlanta Falcons", "price": 1.59}, {"name": "Seattle Seahawks", "price": 2.42}]}]}, {"key": "williamhill_us", "title": "Caesars", "markets": [{"key": "h2h", "last_update": "2024-08-23T14:19:19Z", "outcomes": [{"name": "Atlanta Falcons", "price": 1.53}, {"name": "Seattle Seahawks", "price": 2.58}]}]}]}