{"id": "6214d50d3a5b442078f670ff8e08945e", "sport_key": "americanfootball_nfl", "sport_title": "NFL", "commence_time": "2024-11-10T21:05:00Z", "home_team": "Los Angeles Chargers", "away_team": "Tennessee Titans", "bookmakers": [{"key": "draftkings", "title": "DraftKings", "markets": [{"key": "h2h", "last_update": "2024-08-23T14:29:51Z", "outcomes": [{"name": "Los Angeles Chargers", "price": 1.54}, {"name": "Tennessee Titans", "price": 2.54}]}]}, {"key": "williamhill_us", "title": "Caesars", "markets": [{"key": "h2h", "last_update": "2024-08-23T14:19:19Z", "outcomes": [{"name": "Los Angeles Chargers", "price": 1.56}, {"name": "Tennessee Titans", "price": 2.52}]}]}]}