{"id": "8e047915fdc9b7dc77d2276e740f55d2", "sport_key": "americanfootball_nfl", "sport_title": "NFL", "commence_time": "2024-09-24T00:15:00Z", "home_team": "Cincinnati Bengals", "away_team": "Washington Commanders", "bookmakers": [{"key": "draftkings", "title": "DraftKings", "markets": [{"key": "h2h", "last_update": "2024-08-23T14:29:51Z", "outcomes": [{"name": "Cincinnati Bengals", "price": 1.29}, {"name": "Washington Commanders", "price": 3.75}]}]}, {"key": "williamhill_us", "title": "Caesars", "markets": [{"key": "h2h", "last_update": "2024-08-23T14:19:19Z", "outcomes": [{"name": "Cincinnati Bengals", "price": 1.36}, {"name": "Washington Commanders", "price": 3.22}]}]}]}