{"id": "d94f808523ced7460f7c88c758c481f5", "sport_key": "americanfootball_nfl", "sport_title": "NFL", "commence_time": "2024-09-10T00:20:00Z", "home_team": "San Francisco 49ers", "away_team": "New York Jets", "bookmakers": [{"key": "draftkings", "title": "DraftKings", "markets": [{"key": "h2h", "last_update": "2024-08-23T14:28:04Z", "outcomes": [{"name": "New York Jets", "price": 2.64}, {"name": "San Francisco 49ers", "price": 1.51}]}]}, {"key": "fanduel", "title": "FanDuel", "markets": [{"key": "h2h", "last_update": "2024-08-23T14:28:04Z", "outcomes": [{"name": "New York Jets", "price": 2.68}, {"name": "San Francisco 49ers", "price": 1.5}]}]}, {"key": "betrivers", "title": "BetRivers", "markets": [{"key": "h2h", "last_update": "2024-08-23T14:28:04Z", "outcomes": [{"name": "New York Jets", "price": 2.75}, {"name": "San Francisco 49ers", "price": 1.47}]}]}, {"key": "betonlineag", "title": "BetOnline.ag", "markets": [{"key": "h2h", "last_update": "2024-08-23T14:28:03Z", "outcomes": [{"name": "New York Jets", "price": 2.8}, {"name": "San Francisco 49ers", "price": 1.48}]}]}, {"key": "lowvig", "title": "LowVig.ag", "markets": [{"key": "h2h", "last_update": "2024-08-23T14:28:04Z", "outcomes": [{"name": "New York Jets", "price": 2.8}, {"name": "San Francisco 49ers", "price": 1.48}]}]}, {"key": "williamhill_us", "title": "Caesars", "markets": [{"key": "h2h", "last_update": "2024-08-23T14:19:19Z", "outcomes": [{"name": "New York Jets", "price": 2.8}, {"name": "San Francisco 49ers", "price": 1.45}]}]}, {"key": "betmgm", "title": "BetMGM", "markets": [{"key": "h2h", "last_update": "2024-08-23T14:28:04Z", "outcomes": [{"name": "New York Jets", "price": 2.75}, {"name": "San Francisco 49ers", "price": 1.48}]}]}, {"key": "betus", "title": "BetUS", "markets": [{"key": "h2h", "last_update": "2024-08-23T14:28:05Z", "outcomes": [{"name": "New York Jets", "price": 2.85}, {"name": "San Francisco 49ers", "price": 1.45}]}]}, {"key": "bovada", "title": "Bovada", "markets": [{"key": "h2h", "last_update": "2024-08-23T14:28:04Z", "outcomes": [{"name": "New York Jets", "price": 2.7}, {"name": "San Francisco 49ers", "price": 1.5}]}]}]}